{
  "archives": [
    {
      "id": 8,
      "title": "Test of silent mode",
      "description": "",
      "category": "feature",
      "status": "todo",
      "created": "2025-03-29T13:56:15.651Z",
      "lastUpdated": "2025-03-29T13:56:15.652Z",
      "createdBy": "DVC2",
      "branch": "main",
      "relatedFiles": [
        "--silent"
      ],
      "comments": [],
      "archived": {
        "date": "2025-03-30T07:24:37.877Z",
        "reason": "Task is no longer needed"
      }
    },
    {
      "id": 11,
      "title": "Fixed global options issue",
      "description": "",
      "category": "bugfix",
      "status": "todo",
      "created": "2025-03-29T14:04:25.496Z",
      "lastUpdated": "2025-03-29T14:04:25.498Z",
      "createdBy": "DVC2",
      "branch": "main",
      "relatedFiles": [],
      "comments": [],
      "archived": {
        "date": "2025-03-30T07:24:37.943Z",
        "reason": "Duplicate of another task"
      }
    }
  ]
}